torchcache/__init__.py
torchcache/logging.py
torchcache/torchcache.py
torchcache-0.6.0.dist-info/LICENSE
torchcache-0.6.0.dist-info/METADATA
torchcache-0.6.0.dist-info/WHEEL
torchcache-0.6.0.dist-info/RECORD
