Metadata-Version: 2.3
Name: torchcache
Version: 0.6.0
Summary: Cache PyTorch module outputs on the fly
License: MIT
Author: Eren Akbiyik
Author-email: erenakbiyik@gmail.com
Requires-Python: >=3.9
Classifier: License :: OSI Approved :: MIT License
Classifier: Programming Language :: Python :: 3
Classifier: Programming Language :: Python :: 3.9
Classifier: Programming Language :: Python :: 3.10
Classifier: Programming Language :: Python :: 3.11
Classifier: Programming Language :: Python :: 3.12
Classifier: Programming Language :: Python :: 3.13
Requires-Dist: torch (>=2.0.0)
Requires-Dist: zstd (>=1.5.5.1,<2.0.0.0)
